{
  "run": {
    "command": "nx affected --target=build --base=origin/dev --parallel --configuration=staging",
    "startTime": "2025-01-10T12:23:35.580Z",
    "endTime": "2025-01-10T12:23:52.834Z",
    "inner": false
  },
  "tasks": [
    {
      "taskId": "solid-core:build:staging",
      "target": "build",
      "projectName": "solid-core",
      "hash": "14848051796025268551",
      "startTime": "2025-01-10T12:23:35.592Z",
      "endTime": "2025-01-10T12:23:37.247Z",
      "params": "",
      "cacheStatus": "local-cache-hit",
      "status": 0
    },
    {
      "taskId": "solid-slideshow:build:staging",
      "target": "build",
      "projectName": "solid-slideshow",
      "hash": "9108203282532309547",
      "startTime": "2025-01-10T12:23:38.701Z",
      "endTime": "2025-01-10T12:23:40.138Z",
      "params": "",
      "cacheStatus": "local-cache-hit",
      "status": 0
    },
    {
      "taskId": "solid-glossary:build:staging",
      "target": "build",
      "projectName": "solid-glossary",
      "hash": "6825904900073805776",
      "startTime": "2025-01-10T12:23:38.701Z",
      "endTime": "2025-01-10T12:23:41.518Z",
      "params": "",
      "cacheStatus": "local-cache-hit",
      "status": 0
    },
    {
      "taskId": "solid-profile:build:staging",
      "target": "build",
      "projectName": "solid-profile",
      "hash": "4669922317375976934",
      "startTime": "2025-01-10T12:23:38.702Z",
      "endTime": "2025-01-10T12:23:42.950Z",
      "params": "",
      "cacheStatus": "local-cache-hit",
      "status": 0
    },
    {
      "taskId": "solid-quiz:build:staging",
      "target": "build",
      "projectName": "solid-quiz",
      "hash": "16459495839946246909",
      "startTime": "2025-01-10T12:23:44.195Z",
      "endTime": "2025-01-10T12:23:48.469Z",
      "params": "",
      "cacheStatus": "local-cache-hit",
      "status": 0
    },
    {
      "taskId": "solid-skeleton:build:staging",
      "target": "build",
      "projectName": "solid-skeleton",
      "hash": "15485214515346477698",
      "startTime": "2025-01-10T12:23:49.511Z",
      "endTime": "2025-01-10T12:23:50.773Z",
      "params": "",
      "cacheStatus": "local-cache-hit",
      "status": 0
    },
    {
      "taskId": "ais:build:staging",
      "target": "build",
      "projectName": "ais",
      "hash": "12646317237262521939",
      "startTime": "2025-01-10T12:23:52.151Z",
      "endTime": "2025-01-10T12:23:52.247Z",
      "params": "",
      "cacheStatus": "local-cache-hit",
      "status": 0
    },
    {
      "taskId": "geomat:build:staging",
      "target": "build",
      "projectName": "geomat",
      "hash": "12420279213927321752",
      "startTime": "2025-01-10T12:23:52.152Z",
      "endTime": "2025-01-10T12:23:52.325Z",
      "params": "",
      "cacheStatus": "local-cache-hit",
      "status": 0
    },
    {
      "taskId": "dive:build:staging",
      "target": "build",
      "projectName": "dive",
      "hash": "7058348502646551122",
      "startTime": "2025-01-10T12:23:52.151Z",
      "endTime": "2025-01-10T12:23:52.385Z",
      "params": "",
      "cacheStatus": "local-cache-hit",
      "status": 0
    },
    {
      "taskId": "planty:build:staging",
      "target": "build",
      "projectName": "planty",
      "hash": "13533077310971838412",
      "startTime": "2025-01-10T12:23:52.442Z",
      "endTime": "2025-01-10T12:23:52.660Z",
      "params": "",
      "cacheStatus": "local-cache-hit",
      "status": 0
    },
    {
      "taskId": "wabe:build:staging",
      "target": "build",
      "projectName": "wabe",
      "hash": "3818705369663789150",
      "startTime": "2025-01-10T12:23:52.526Z",
      "endTime": "2025-01-10T12:23:52.720Z",
      "params": "",
      "cacheStatus": "local-cache-hit",
      "status": 0
    }
  ]
}